fastapi_interface/__init__.py
fastapi_interface/constants.py
fastapi_interface/dependencies.py
fastapi_interface/main.py
fastapi_interface/middlewares.py
fastapi_interface/schemas/__init__.py
fastapi_interface/schemas/base.py
fastapi_interface/schemas/user.py
fastapi_interface/views/__init__.py
fastapi_interface/views/health.py
fastapi_interface/views/hostname.py
fastapi_interface-0.3.1.dist-info/WHEEL
fastapi_interface-0.3.1.dist-info/METADATA
fastapi_interface-0.3.1.dist-info/RECORD
