Metadata-Version: 2.1
Name: fastapi-interface
Version: 0.3.1
Summary: for DRY in microservices
Author: koevgeny10
Author-email: koevgeny10@gmail.com
Requires-Python: >=3.10,<4.0
Classifier: Programming Language :: Python :: 3
Classifier: Programming Language :: Python :: 3.10
Requires-Dist: email-validator (>=1.2.1,<2.0.0)
Requires-Dist: fastapi (>=0.78.0,<0.79.0)
Requires-Dist: orjson (>=3.6.8,<4.0.0)
Requires-Dist: python-jose[cryptography] (>=3.3.0,<4.0.0)
Requires-Dist: python-multipart (>=0.0.5,<0.0.6)
